{
  "__type__": "cc.Mesh",
  "_name": "",
  "_objFlags": 0,
  "__editorExtras__": {},
  "_native": ".bin",
  "_struct": {
    "primitives": [
      {
        "primitiveMode": 7,
        "jointMapIndex": 0,
        "vertexBundelIndices": [
          0
        ],
        "indexView": {
          "offset": 10480,
          "length": 755,
          "count": 1260,
          "stride": 4
        }
      }
    ],
    "vertexBundles": [
      {
        "view": {
          "offset": 0,
          "length": 10480,
          "count": 253,
          "stride": 72
        },
        "attributes": [
          {
            "name": "a_position",
            "format": 32,
            "isNormalized": false
          },
          {
            "name": "a_normal",
            "format": 32,
            "isNormalized": false
          },
          {
            "name": "a_texCoord",
            "format": 21,
            "isNormalized": false
          },
          {
            "name": "a_tangent",
            "format": 44,
            "isNormalized": false
          },
          {
            "name": "a_joints",
            "format": 42,
            "isNormalized": false
          },
          {
            "name": "a_weights",
            "format": 44,
            "isNormalized": false
          }
        ]
      }
    ],
    "minPosition": {
      "x": -0.1912584751844406,
      "y": -0.056492310017347336,
      "z": -1.903045654296875
    },
    "maxPosition": {
      "x": 0.1912584751844406,
      "y": 0.056492310017347336,
      "z": 1.9030457735061646
    },
    "jointMaps": [
      [
        0,
        1,
        2
      ]
    ],
    "encoded": true,
    "compressed": true
  },
  "_hash": 3966444420,
  "_allowDataAccess": true
}