{
  "__type__": "cc.Mesh",
  "_name": "",
  "_objFlags": 0,
  "__editorExtras__": {},
  "_native": ".bin",
  "_struct": {
    "primitives": [
      {
        "primitiveMode": 7,
        "vertexBundelIndices": [
          0
        ],
        "indexView": {
          "offset": 61908,
          "length": 190,
          "count": 504,
          "stride": 4
        }
      },
      {
        "primitiveMode": 7,
        "vertexBundelIndices": [
          1
        ],
        "indexView": {
          "offset": 62100,
          "length": 151,
          "count": 372,
          "stride": 4
        }
      },
      {
        "primitiveMode": 7,
        "vertexBundelIndices": [
          2
        ],
        "indexView": {
          "offset": 62252,
          "length": 19,
          "count": 6,
          "stride": 4
        }
      },
      {
        "primitiveMode": 7,
        "vertexBundelIndices": [
          3
        ],
        "indexView": {
          "offset": 62272,
          "length": 2138,
          "count": 2475,
          "stride": 4
        }
      },
      {
        "primitiveMode": 7,
        "vertexBundelIndices": [
          4
        ],
        "indexView": {
          "offset": 64412,
          "length": 135,
          "count": 324,
          "stride": 4
        }
      },
      {
        "primitiveMode": 7,
        "vertexBundelIndices": [
          5
        ],
        "indexView": {
          "offset": 64548,
          "length": 3848,
          "count": 3810,
          "stride": 4
        }
      },
      {
        "primitiveMode": 7,
        "vertexBundelIndices": [
          6
        ],
        "indexView": {
          "offset": 68396,
          "length": 19,
          "count": 6,
          "stride": 4
        }
      },
      {
        "primitiveMode": 7,
        "vertexBundelIndices": [
          7
        ],
        "indexView": {
          "offset": 68416,
          "length": 127,
          "count": 330,
          "stride": 4
        }
      }
    ],
    "vertexBundles": [
      {
        "view": {
          "offset": 0,
          "length": 6886,
          "count": 493,
          "stride": 24
        },
        "attributes": [
          {
            "name": "a_position",
            "format": 29,
            "isNormalized": false
          },
          {
            "name": "a_normal",
            "format": 29,
            "isNormalized": false
          },
          {
            "name": "a_texCoord",
            "format": 18,
            "isNormalized": false
          },
          {
            "name": "a_tangent",
            "format": 41,
            "isNormalized": false
          }
        ]
      },
      {
        "view": {
          "offset": 6888,
          "length": 3176,
          "count": 223,
          "stride": 24
        },
        "attributes": [
          {
            "name": "a_position",
            "format": 29,
            "isNormalized": false
          },
          {
            "name": "a_normal",
            "format": 29,
            "isNormalized": false
          },
          {
            "name": "a_texCoord",
            "format": 18,
            "isNormalized": false
          },
          {
            "name": "a_tangent",
            "format": 41,
            "isNormalized": false
          }
        ]
      },
      {
        "view": {
          "offset": 10080,
          "length": 132,
          "count": 6,
          "stride": 24
        },
        "attributes": [
          {
            "name": "a_position",
            "format": 29,
            "isNormalized": false
          },
          {
            "name": "a_normal",
            "format": 29,
            "isNormalized": false
          },
          {
            "name": "a_texCoord",
            "format": 18,
            "isNormalized": false
          },
          {
            "name": "a_tangent",
            "format": 41,
            "isNormalized": false
          }
        ]
      },
      {
        "view": {
          "offset": 10224,
          "length": 21769,
          "count": 1298,
          "stride": 24
        },
        "attributes": [
          {
            "name": "a_position",
            "format": 29,
            "isNormalized": false
          },
          {
            "name": "a_normal",
            "format": 29,
            "isNormalized": false
          },
          {
            "name": "a_texCoord",
            "format": 18,
            "isNormalized": false
          },
          {
            "name": "a_tangent",
            "format": 41,
            "isNormalized": false
          }
        ]
      },
      {
        "view": {
          "offset": 32016,
          "length": 2954,
          "count": 168,
          "stride": 24
        },
        "attributes": [
          {
            "name": "a_position",
            "format": 29,
            "isNormalized": false
          },
          {
            "name": "a_normal",
            "format": 29,
            "isNormalized": false
          },
          {
            "name": "a_texCoord",
            "format": 18,
            "isNormalized": false
          },
          {
            "name": "a_tangent",
            "format": 41,
            "isNormalized": false
          }
        ]
      },
      {
        "view": {
          "offset": 34992,
          "length": 22166,
          "count": 1382,
          "stride": 24
        },
        "attributes": [
          {
            "name": "a_position",
            "format": 29,
            "isNormalized": false
          },
          {
            "name": "a_normal",
            "format": 29,
            "isNormalized": false
          },
          {
            "name": "a_texCoord",
            "format": 18,
            "isNormalized": false
          },
          {
            "name": "a_tangent",
            "format": 41,
            "isNormalized": false
          }
        ]
      },
      {
        "view": {
          "offset": 57168,
          "length": 147,
          "count": 6,
          "stride": 24
        },
        "attributes": [
          {
            "name": "a_position",
            "format": 29,
            "isNormalized": false
          },
          {
            "name": "a_normal",
            "format": 29,
            "isNormalized": false
          },
          {
            "name": "a_texCoord",
            "format": 18,
            "isNormalized": false
          },
          {
            "name": "a_tangent",
            "format": 41,
            "isNormalized": false
          }
        ]
      },
      {
        "view": {
          "offset": 57336,
          "length": 4572,
          "count": 314,
          "stride": 24
        },
        "attributes": [
          {
            "name": "a_position",
            "format": 29,
            "isNormalized": false
          },
          {
            "name": "a_normal",
            "format": 29,
            "isNormalized": false
          },
          {
            "name": "a_texCoord",
            "format": 18,
            "isNormalized": false
          },
          {
            "name": "a_tangent",
            "format": 41,
            "isNormalized": false
          }
        ]
      }
    ],
    "minPosition": {
      "x": -1.690710186958313,
      "y": -2.122286796569824,
      "z": -1.603482961654663
    },
    "maxPosition": {
      "x": 1.8252606391906738,
      "y": 5.546161651611328,
      "z": 1.708517074584961
    },
    "quantized": true,
    "encoded": true,
    "compressed": true
  },
  "_hash": 2629122329,
  "_allowDataAccess": true
}